gustavgrad/__init__.py
gustavgrad/function.py
gustavgrad/loss.py
gustavgrad/module.py
gustavgrad/optim.py
gustavgrad/py.typed
gustavgrad/tensor.py
gustavgrad-0.2.0.dist-info/LICENSE
gustavgrad-0.2.0.dist-info/WHEEL
gustavgrad-0.2.0.dist-info/METADATA
gustavgrad-0.2.0.dist-info/RECORD
