Metadata-Version: 2.1
Name: gustavgrad
Version: 0.2.0
Summary: 
Home-page: https://github.com/gustavgransbo/gustavgrad
License: MIT
Author: Gustav Gränsbo
Author-email: gustav.gransbo@gmail.com
Requires-Python: >=3.7,<4.0
Classifier: License :: OSI Approved :: MIT License
Classifier: Programming Language :: Python :: 3
Classifier: Programming Language :: Python :: 3.7
Classifier: Programming Language :: Python :: 3.8
Requires-Dist: numpy (>=1.19.0,<2.0.0)
Project-URL: Repository, https://github.com/gustavgransbo/gustavgrad
